root_vortex/__init__.py
root_vortex/__main__.py
root_vortex/main.py
root_vortex-3.0.0.dist-info/METADATA
root_vortex-3.0.0.dist-info/WHEEL
root_vortex-3.0.0.dist-info/entry_points.txt
root_vortex-3.0.0.dist-info/top_level.txt
root_vortex-3.0.0.dist-info/RECORD
