Metadata-Version: 2.2
Name: root-vortex
Version: 3.0.0
Summary: Quantum AI Secure Root Execution
Home-page: https://github.com/YOUR_GITHUB_USERNAME/root-vortex
Author: Sean Tichenor
Classifier: Programming Language :: Python :: 3
Classifier: License :: OSI Approved :: MIT License
Classifier: Operating System :: POSIX :: Linux
Dynamic: author
Dynamic: classifier
Dynamic: description
Dynamic: description-content-type
Dynamic: home-page
Dynamic: summary
